gridr/cdylib/__init__.py
gridr/cdylib/_libgridr.abi3.so
gridr/chain/fft_filtering_chain.py
gridr/chain/grid_mask_chain.py
gridr/chain/grid_resampling_chain.py
gridr/core/convolution/__init__.py
gridr/core/convolution/fft_filtering.py
gridr/core/filter/__init__.py
gridr/core/filter/filter.py
gridr/core/filter/frequential_interp_2d.py
gridr/core/filter/lattice.py
gridr/core/grid/__init__.py
gridr/core/grid/grid_antialiasing.py
gridr/core/grid/grid_commons.py
gridr/core/grid/grid_mask.py
gridr/core/grid/grid_rasterize.py
gridr/core/grid/grid_resampling.py
gridr/core/grid/grid_utils.py
gridr/core/interp/__init__.py
gridr/core/interp/bspline_prefiltering.py
gridr/core/interp/interpolator.py
gridr/core/utils/__init__.py
gridr/core/utils/array_pad.py
gridr/core/utils/array_utils.py
gridr/core/utils/array_window.py
gridr/core/utils/chunks.py
gridr/core/utils/fft.py
gridr/core/utils/parameters.py
gridr/io/__init__.py
gridr/io/common.py
gridr/io/tile.py
gridr/misc/__init__.py
gridr/misc/mandrill.py
gridr/scaling/__init__.py
gridr/scaling/shmutils.py
gridr-0.5.1.dist-info/METADATA
gridr-0.5.1.dist-info/WHEEL
gridr-0.5.1.dist-info/top_level.txt
gridr-0.5.1.dist-info/RECORD
gridr-0.5.1.dist-info/licenses/LICENSE
