Metadata-Version: 2.4
Name: gridr
Version: 0.5.1
Summary: Geometric and Radiometric Image Data Resampling
Author-email: CNES <gridr-cnes@cnes.fr>
License-Expression: Apache-2.0
Project-URL: Homepage, https://gridr.readthedocs.io
Project-URL: Documentation, https://gridr.readthedocs.io/en/latest/
Project-URL: Repository, https://github.com/CNES/gridr
Project-URL: Issues, https://github.com/CNES/gridr/issues
Project-URL: Changelog, https://github.com/CNES/gridr/blob/main/CHANGELOG.md
Classifier: Development Status :: 4 - Beta
Classifier: Environment :: Console
Classifier: Intended Audience :: Developers
Classifier: Intended Audience :: End Users/Desktop
Classifier: Intended Audience :: Science/Research
Classifier: Operating System :: OS Independent
Classifier: Programming Language :: Python
Classifier: Programming Language :: Python :: 3
Classifier: Programming Language :: Python :: 3 :: Only
Classifier: Programming Language :: Python :: 3.10
Classifier: Programming Language :: Python :: 3.11
Classifier: Programming Language :: Python :: 3.12
Classifier: Programming Language :: Python :: 3.13
Classifier: Programming Language :: Python :: 3.14
Classifier: Programming Language :: Rust
Classifier: Topic :: Software Development :: Libraries :: Python Modules
Classifier: Typing :: Typed
Requires-Python: >=3.10
License-File: LICENSE
Requires-Dist: numpy>=1.25
Requires-Dist: scipy>=1.10.1
Requires-Dist: rasterio>=1.3.11
Requires-Dist: shapely>=2.0.6
Requires-Dist: typing_extensions>=4.15.0
Dynamic: license-file
